irisml/tasks/create_yolov9_dataset.py
irisml/tasks/load_yolov9_prediction_results.py
irisml/tasks/create_yolov9_detection_model/__init__.py
irisml/tasks/create_yolov9_detection_model/create_yolov9_detection_model.py
irisml/tasks/create_yolov9_detection_model/resources/gelan.yaml
irisml/tasks/create_yolov9_detection_model/resources/gelanc.yaml
irisml/tasks/create_yolov9_detection_model/resources/gelane.yaml
irisml/tasks/create_yolov9_detection_model/resources/yolov9.yaml
irisml/tasks/create_yolov9_detection_model/resources/yolov9c.yaml
irisml/tasks/create_yolov9_detection_model/resources/yolov9e.yaml
irisml_tasks_yolov9-0.0.6.dist-info/LICENSE
irisml_tasks_yolov9-0.0.6.dist-info/METADATA
irisml_tasks_yolov9-0.0.6.dist-info/WHEEL
irisml_tasks_yolov9-0.0.6.dist-info/top_level.txt
irisml_tasks_yolov9-0.0.6.dist-info/RECORD
