Metadata-Version: 2.1
Name: irisml-tasks-yolov9
Version: 0.0.6
Requires-Python: >=3.10
License-File: LICENSE
Requires-Dist: irisml
Requires-Dist: pyyolov9 <1
